nonebot_plugin_pokemonfusion/__init__.py
nonebot_plugin_pokemonfusion/resources/pokemons.json
nonebot_plugin_pokemonfusion-1.1.2.dist-info/LICENSE
nonebot_plugin_pokemonfusion-1.1.2.dist-info/METADATA
nonebot_plugin_pokemonfusion-1.1.2.dist-info/WHEEL
nonebot_plugin_pokemonfusion-1.1.2.dist-info/top_level.txt
nonebot_plugin_pokemonfusion-1.1.2.dist-info/RECORD
